{"cameraMode":{"drawMode":0,"name":"Shaded","section":"Shading Mode"},"sceneLighting":false,"audioPlay":false,"sceneViewState":{"showFog":true,"showMaterialUpdate":false,"showSkybox":false,"showFlares":true,"showImageEffects":true,"showParticleSystems":true},"in2DMode":false,"pivot":{"x":47.071533203125,"y":14.878549575805664,"z":14.41362476348877},"rotation":{"x":0.28912702202796938,"y":0.7105408310890198,"z":-0.46634814143180849,"w":0.44052672386169436},"size":5.753494739532471,"orthographic":false}